pingdomv3/__init__.py
pingdomv3/logger.py
pingdomv3/pingdomv3.py
pingdomv3-1.1.0.dist-info/LICENSE.txt
pingdomv3-1.1.0.dist-info/METADATA
pingdomv3-1.1.0.dist-info/WHEEL
pingdomv3-1.1.0.dist-info/top_level.txt
pingdomv3-1.1.0.dist-info/RECORD
