Metadata-Version: 2.1
Name: pingdomv3
Version: 1.1.0
Summary: Pingdom v3 redeveloped
Home-page: https://github.com/jinnis423/pingdomv3
Author: Jinnis
Author-email: jinnis.developer@gmail.com
Classifier: Programming Language :: Python :: 3
Classifier: Operating System :: OS Independent
Requires-Python: >=3.6
License-File: LICENSE.txt
